.gitignore
CHANGES.txt
COPYRIGHT.txt
LICENSE.txt
MANIFEST.in
README.txt
bootstrap.py
buildout.cfg
setup.py
src/z3c/__init__.py
src/z3c.webdriver.egg-info/PKG-INFO
src/z3c.webdriver.egg-info/SOURCES.txt
src/z3c.webdriver.egg-info/dependency_links.txt
src/z3c.webdriver.egg-info/namespace_packages.txt
src/z3c.webdriver.egg-info/not-zip-safe
src/z3c.webdriver.egg-info/requires.txt
src/z3c.webdriver.egg-info/top_level.txt
src/z3c/webdriver/README.txt
src/z3c/webdriver/__init__.py
src/z3c/webdriver/browser.py
src/z3c/webdriver/server.py
src/z3c/webdriver/testing.py
src/z3c/webdriver/tests/__init__.py
src/z3c/webdriver/tests/ajax.txt
src/z3c/webdriver/tests/browser.txt
src/z3c/webdriver/tests/controls.txt
src/z3c/webdriver/tests/jquery-1.7.1.js
src/z3c/webdriver/tests/server.txt
src/z3c/webdriver/tests/tests.py