Metadata-Version: 1.1
Name: z3c.webdriver
Version: 0.0.1
Summary: A wrapper around selenium webdriver and some tools
Home-page: https://pypi.python.org/pypi/z3c.webdriver
Author: Adam Groszer and the Zope Community
Author-email: zope-dev@zope.org
License: ZPL 2.1
Keywords: selenium webdriver phantomjs
Platform: UNKNOWN
Classifier: Development Status :: 3 - Alpha
Classifier: Environment :: Web Environment
Classifier: Intended Audience :: Developers
Classifier: License :: OSI Approved :: Zope Public License
Classifier: Programming Language :: Python
Classifier: Programming Language :: Python :: 2
Classifier: Programming Language :: Python :: 2.6
Classifier: Programming Language :: Python :: 2.7
Classifier: Programming Language :: Python :: 3
Classifier: Programming Language :: Python :: 3.3
Classifier: Programming Language :: Python :: Implementation :: CPython
Classifier: Natural Language :: English
Classifier: Operating System :: OS Independent
Classifier: Topic :: Internet :: WWW/HTTP
Classifier: Topic :: Software Development :: Testing
